Workbook

Sheet MVP Instructions
A1: Offline Game Matchmaking — MVP Structure V2
A2: Updated with credibility score, rankings, Estimation calculator, leaderboards, venue funnel, incidents, captains, and Make operations flow.
A4: Section | B4: What This Workbook Contains
A5: Core idea | B5: Offline game matchmaking platform connecting players to other players and approved venues.
A6: Main rules | B6: No poker, no gambling, no private places, no harassment, no unapproved venues.
A7: Player model | B7: Players register through WhatsApp/form with games, preferred locations, availability, consent, and cost-splitting acceptance.
A8: Venue model | B8: Cafés/venues subscribe, sign an agreement, and become approved before receiving players.
A9: Automation model | B9: Use Make for deterministic workflows; use AI for matching suggestions, message drafting, incident triage, and reporting.
A10: MVP control | B10: Admin approval is required before match invitations are automated at scale.
A11: Important separation | B11: Credibility score = trust/reliability. Ranking score = game performance. Do not mix them.

Sheet Dashboard
A1: Offline Game Matchmaking — Dashboard V2
A2: Control view for launch readiness, player trust, venue supply, incidents, and automation progress.
A4: Metric | B4: Value | C4: Why It Matters | E4: MVP Funnel Stage | F4: Owner | G4: Manual Now | H4: Automation Later | I4: Done?
A5: Registered Players | B5: =COUNTA(Players!A5:A200) -> 5 | C5: Player database size | E5: Player awareness | F5: Marwan | G5: Reels, ads, website, word of mouth | H5: Track source/campaign | I5: No
A6: Active Players | B6: =COUNTIF(Players!U5:U200,"Active") -> 5 | C6: Ready players | E6: Player registration | F6: Abdelrahman | G6: WhatsApp/Google form | H6: Auto-fill Players table | I6: No
A7: Average Credibility | B7: =ROUND(AVERAGEIF(Players!AD5:AD200,">0"),1) -> 69.4 | C7: Trust health | E7: Venue qualification | F7: Marwan | G7: Call/meeting + proposal | H7: Venue onboarding workflow | I7: No
A8: Competition Eligible Players | B8: =COUNTIF(Players!AF5:AF200,"Yes") -> 4 | C8: Ready for competitions | E8: Matching | F8: Both | G8: Filter manually by game/location/time/cost | H8: AI matching recommendation | I8: No
A9: Open Game Requests | B9: =COUNTIF('Game Requests'!O5:O200,"Open") -> 2 | C9: Demand pipeline | E9: Admin approval | F9: Marwan | G9: Approve proposed matches | H9: Admin dashboard trigger | I9: No
A10: Approved Venues | B10: =COUNTIF(Venues!M5:M200,"Approved") -> 2 | C10: Supply readiness | E10: WhatsApp invitation | F10: Abdelrahman | G10: Manual test messages | H10: Make + WhatsApp templates | I10: No
A11: Open Incidents | B11: =COUNTIFS('Reports & Incidents'!L5:L200,"<>Resolved",'Reports & Incidents'!L5:L200,"<>") -> 2 | C11: Safety/admin workload | E11: Score/rating | F11: Abdelrahman | G11: Form after game | H11: Automated post-game flow | I11: No
A12: Public Leaderboard Rows | B12: =COUNTIF(Leaderboards!L5:L200,"Public") -> 3 | C12: Community/marketing asset | E12: Incidents | F12: Marwan | G12: Manual review | H12: AI triage + admin queue | I12: No
A13: Active Venue Subscriptions | B13: =COUNTIF('Venue Performance'!F5:F200,"Active") -> 2 | C13: Venue business model

Sheet Games Catalog
A1: Games Catalog
A2: Allowed games only. No poker, no gambling, no betting.
A4: Game_ID | B4: Game | C4: Category | D4: Required Players | E4: Venue Type | F4: Ranking Mode | G4: Score Type | H4: Allowed? | I4: Notes
A5: G001 | B5: Estimation | C5: Card/Social | D5: 4 | E5: Café / board game café | F5: Individual | G5: Estimation calculator | H5: Yes | I5: No betting
A6: G002 | B6: Tarneeb | C6: Card/Social | D6: 4 | E6: Café / board game café | F6: Team/Individual | G6: Manual score | H6: Yes | I6: No betting
A7: G003 | B7: Basra | C7: Card/Social | D7: 2 | E7: Café / board game café | F7: Individual | G7: Manual score | H7: Yes | I7: No betting
A8: G004 | B8: UNO | C8: Card/Social | D8: 2 | E8: Café / board game café | F8: Individual | G8: Manual score | H8: Yes
A9: G005 | B9: Chess | C9: Board/Mind | D9: 2 | E9: Board game café / club | F9: Individual | G9: Win/loss/draw | H9: Yes
A10: G006 | B10: Backgammon | C10: Board/Mind | D10: 2 | E10: Café / board game café | F10: Individual | G10: Win/loss | H10: Yes
A11: G007 | B11: Billiards | C11: Table Game | D11: 2 | E11: Billiards hall | F11: Individual | G11: Win/loss | H11: Yes
A12: G008 | B12: FIFA 2026 | C12: Console | D12: 2 | E12: PlayStation center | F12: Individual/Team | G12: Win/loss/score | H12: Yes
A13: G009 | B13: Call of Duty | C13: Console | D13: 2 | E13: Gaming lounge | F13: Team | G13: Match score | H13: Yes
A14: G010 | B14: League of Legends | C14: PC Game | D14: 10 | E14: Internet café / gaming lounge | F14: Team | G14: Match result | H14: Yes
A15: G011 | B15: Valorant | C15: PC Game | D15: 10 | E15: Internet café / gaming lounge | F15: Team | G15: Match result | H15: Yes
A16: G012 | B16: Football | C16: Sport | D16: 10 | E16: Football court | F16: Team | G16: Score | H16: Yes | I16: 5v5 MVP
A17: G013 | B17: Tennis | C17: Sport | D17: 2 | E17: Tennis court | F17: Individual | G17: Score | H17: Yes
A18: G014 | B18: Padel | C18: Sport | D18: 4 | E18: Padel court | F18: Team | G18: Score | H18: Yes
A19: G999 | B19: Poker | C19: Excluded | D19: 0 | E19: Not allowed | F19: None | G19: None | H19: No | I19: Excluded: gambling/betting risk

Sheet Lookup Lists
A1: Lookup Lists
A2: Dropdown-ready values for forms, sheets, and Make scenario filters.
A4: Game Category | B4: Player Status | C4: Venue Status | D4: Match Status | E4: Confirmation Status | F4: Incident Type | G4: Severity | H4: Subscription Tier | I4: Visibility | J4: Dispute Status
A5: Card/Social | B5: New | C5: Lead | D5: Draft | E5: Pending | F5: No-show | G5: Low | H5: Basic | I5: Public | J5: Clean
A6: Board/Mind | B6: Active | C6: Qualified | D6: Proposed | E6: Accepted | F6: Harassment | G6: Medium | H6: Featured | I6: Internal | J6: Minor issue
A7: Table Game | B7: Suspended | C7: Proposal sent | D7: Waiting confirmations | E7: Declined | F7: Cheating | G7: High | H7: Competition Partner | I7: Hidden | J7: Under review
A8: Console | B8: Banned | C8: Contract pending | D8: Confirmed | E8: No response | F8: Cost dispute | G8: Critical | H8: Sponsor | I8: Internal/Public | J8: Disputed
A9: PC Game | B9: Inactive | C9: Active | D9: Completed | E9: No-show | F9: Venue complaint | J9: Resolved
A10: Sport | C10: Paused | D10: Cancelled | F10: Fake profile
A11: Other | C11: Cancelled | D11: Failed | F11: Disrespect

Sheet Players
A1: Players
A2: Player master table. The bot and Make read from here for matching, consent, opt-in, credibility, and eligibility.
A4: Player_ID | B4: Name | C4: WhatsApp Number | D4: Age | E4: Gender | F4: Job Title | G4: Main Area | H4: Preferred Locations | I4: Max Travel Time (min) | J4: Games Can Play | K4: Primary Game | L4: Game Category | M4: Preferred Days | N4: Free From | O4: Free To | P4: Skill Level | Q4: Preferred Venue Type | R4: Accepts Cost Split? | S4: Approved Public Venues Only? | T4: Privacy & Rules Consent? | U4: Status | V4: Avg Rating | W4: Games Completed | X4: No Shows | Y4: Reliability Score | Z4: Source | AA4: WhatsApp Opt-in? | AB4: Marketing Consent? | AC4: Opt-out Status | AD4: Credibility Score | AE4: Verification Level | AF4: Competition Eligible? | AG4: Ranking Visibility | AH4: Admin Notes
A5: P001 | B5: Ahmed Hassan | C5: +201000000001 | D5: 32 | E5: Male | F5: Doctor | G5: New Cairo | H5: New Cairo, Nasr City | I5: 20 | J5: Estimation, Chess, Billiards | K5: Estimation | L5: Card/Social | M5: Thu, Fri | N5: 8:00 PM | O5: 10:00 PM | P5: Casual | Q5: Café | R5: Yes | S5: Yes | T5: Yes | U5: Active | V5: 5 | W5: 1 | X5: 0 | Y5: Good | Z5: Instagram Reels | AA5: Yes | AB5: Yes | AC5: No | AD5: =IF(A5="","",MIN(100,MAX(0,70+SUMIF('Credibility Log'!$B:$B,A5,'Credibility Log'!$E:$E)))) -> 77 | AE5: =IF(AD5="","",IFS(AD5>=90,"Level 5 - Ambassador",AD5>=80,"Level 4 - Competition Eligible",AD5>=70,"Level 3 - Trusted",AD5>=60,"Level 2 - Active",AD5>=50,"Level 1 - Watchlist",TRUE,"Level 0 - Restricted")) -> #NAME? | AF5: =IF(AD5="","",IF(AD5>=70,"Yes","No")) -> Yes | AG5: Public leaderboard | AH5: Sample
A6: P002 | B6: Omar Ali | C6: +201000000002 | D6: 28 | E6: Male | F6: Engineer | G6: New Cairo | H6: New Cairo | I6: 15 | J6: Estimation, FIFA 2026 | K6: Estimation | L6: Card/Social | M6: Fri | N6: 8:00 PM | O6: 11:00 PM | P6: Intermediate | Q6: Board Game Café | R6: Yes | S6: Yes | T6: Yes | U6: Active | V6: 4.8 | W6: 1 | X6: 0 | Y6: Good | Z6: Word of Mouth | AA6: Yes | AB6: Yes | AC6: No | AD6: =IF(A6="","",MIN(100,MAX(0,70+SUMIF('Credibility Log'!$B:$B,A6,'Credibility Log'!$E:$E)))) -> 75 | AE6: =IF(AD6="","",IFS(AD6>=90,"Level 5 - Ambassador",AD6>=80,"Level 4 - Competition Eligible",AD6>=70,"Level 3 - Trusted",AD6>=60,"Level 2 - Active",AD6>=50,"Level 1 - Watchlist",TRUE,"Level 0 - Restricted")) -> #NAME? | AF6: =IF(AD6="","",IF(AD6>=70,"Yes","No")) -> Yes | AG6: Public leaderboard | AH6: Sample
A7: P003 | B7: Khaled Samir | C7: +201000000003 | D7: 30 | E7: Male | F7: Accountant | G7: Nasr City | H7: New Cairo, Nasr City | I7: 30 | J7: Estimation, Billiards | K7: Estimation | L7: Card/Social | M7: Fri, Sat | N7: 7:00 PM | O7: 11:00 PM | P7: Casual | Q7: Café | R7: Yes | S7: Yes | T7: Yes | U7: Active | V7: 3.5 | W7: 0 | X7: 1 | Y7: Watch | Z7: Facebook Ads | AA7: Yes | AB7: No | AC7: No | AD7: =IF(A7="","",MIN(100,MAX(0,70+SUMIF('Credibility Log'!$B:$B,A7,'Credibility Log'!$E:$E)))) -> 55 | AE7: =IF(AD7="","",IFS(AD7>=90,"Level 5 - Ambassador",AD7>=80,"Level 4 - Competition Eligible",AD7>=70,"Level 3 - Trusted",AD7>=60,"Level 2 - Active",AD7>=50,"Level 1 - Watchlist",TRUE,"Level 0 - Restricted")) -> #NAME? | AF7: =IF(AD7="","",IF(AD7>=70,"Yes","No")) -> No | AG7: Hidden/Review | AH7: Sample no-show
A8: P004 | B8: Mona Adel | C8: +201000000004 | D8: 26 | E8: Female | F8: Designer | G8: New Cairo | H8: New Cairo, Heliopolis | I8: 20 | J8: Chess, Padel | K8: Chess | L8: Board/Mind | M8: Sat | N8: 6:00 PM | O8: 9:00 PM | P8: Intermediate | Q8: Board Game Café | R8: Yes | S8: Yes | T8: Yes | U8: Active | V8: 5 | W8: 1 | X8: 0 | Y8: Good | Z8: Website | AA8: Yes | AB8: Yes | AC8: No | AD8: =IF(A8="","",MIN(100,MAX(0,70+SUMIF('Credibility Log'!$B:$B,A8,'Credibility Log'!$E:$E)))) -> 70 | AE8: =IF(AD8="","",IFS(AD8>=90,"Level 5 - Ambassador",AD8>=80,"Level 4 - Competition Eligible",AD8>=70,"Level 3 - Trusted",AD8>=60,"Level 2 - Active",AD8>=50,"Level 1 - Watchlist",TRUE,"Level 0 - Restricted")) -> #NAME? | AF8: =IF(AD8="","",IF(AD8>=70,"Yes","No")) -> Yes | AG8: Public leaderboard | AH8: Sample
A9: P005 | B9: Youssef Tarek | C9: +201000000005 | D9: 24 | E9: Male | F9: Student | G9: Sheikh Zayed | H9: Sheikh Zayed, 6th of October | I9: 15 | J9: Padel, FIFA 2026 | K9: Padel | L9: Sport | M9: Fri, Sat | N9: 7:00 PM | O9: 10:00 PM | P9: Beginner | Q9: Padel Court | R9: Yes | S9: Yes | T9: Yes | U9: Active | V9: 4.2 | W9: 0 | X9: 0 | Y9: New | Z9: TikTok | AA9: Yes | AB9: Yes | AC9: No | AD9: =IF(A9="","",MIN(100,MAX(0,70+SUMIF('Credibility Log'!$B:$B,A9,'Credibility Log'!$E:$E)))) -> 70 | AE9: =IF(AD9="","",IFS(AD9>=90,"Level 5 - Ambassador",AD9>=80,"Level 4 - Competition Eligible",AD9>=70,"Level 3 - Trusted",AD9>=60,"Level 2 - Active",AD9>=50,"Level 1 - Watchlist",TRUE,"Level 0 - Restricted")) -> #NAME? | AF9: =IF(AD9="","",IF(AD9>=70,"Yes","No")) -> Yes | AG9: Public leaderboard | AH9: Sample
AD10: =IF(A10="","",MIN(100,MAX(0,70+SUMIF('Credibility Log'!$B:$B,A10,'Credibility Log'!$E:$E)))) | AE10: =IF(AD10="","",IFS(AD10>=90,"Level 5 - Ambassador",AD10>=80,"Level 4 - Competition Eligible",AD10>=70,"Level 3 - Trusted",AD10>=60,"Level 2 - Active",AD10>=50,"Level 1 - Watchlist",TRUE,"Level 0 - Restricted")) | AF10: =IF(AD10="","",IF(AD10>=70,"Yes","No"))
AD11: =IF(A11="","",MIN(100,MAX(0,70+SUMIF('Credibility Log'!$B:$B,A11,'Credibility Log'!$E:$E)))) | AE11: =IF(AD11="","",IFS(AD11>=90,"Level 5 - Ambassador",AD11>=80,"Level 4 - Competition Eligible",AD11>=70,"Level 3 - Trusted",AD11>=60,"Level 2 - Active",AD11>=50,"Level 1 - Watchlist",TRUE,"Level 0 - Restricted")) | AF11: =IF(AD11="","",IF(AD11>=70,"Yes","No"))
AD12: =IF(A12="","",MIN(100,MAX(0,70+SUMIF('Credibility Log'!$B:$B,A12,'Credibility Log'!$E:$E)))) | AE12: =IF(AD12="","",IFS(AD12>=90,"Level 5 - Ambassador",AD12>=80,"Level 4 - Competition Eligible",AD12>=70,"Level 3 - Trusted",AD12>=60,"Level 2 - Active",AD12>=50,"Level 1 - Watchlist",TRUE,"Level 0 - Restricted")) | AF12: =IF(AD12="","",IF(AD12>=70,"Yes","No"))
AD13: =IF(A13="","",MIN(100,MAX(0,70+SUMIF('Credibility Log'!$B:$B,A13,'Credibility Log'!$E:$E)))) | AE13: =IF(AD13="","",IFS(AD13>=90,"Level 5 - Ambassador",AD13>=80,"Level 4 - Competition Eligible",AD13>=70,"Level 3 - Trusted",AD13>=60,"Level 2 - Active",AD13>=50,"Level 1 - Watchlist",TRUE,"Level 0 - Restricted")) | AF13: =IF(AD13="","",IF(AD13>=70,"Yes","No"))
AD14: =IF(A14="","",MIN(100,MAX(0,70+SUMIF('Credibility Log'!$B:$B,A14,'Credibility Log'!$E:$E)))) | AE14: =IF(AD14="","",IFS(AD14>=90,"Level 5 - Ambassador",AD14>=80,"Level 4 - Competition Eligible",AD14>=70,"Level 3 - Trusted",AD14>=60,"Level 2 - Active",AD14>=50,"Level 1 - Watchlist",TRUE,"Level 0 - Restricted")) | AF14: =IF(AD14="","",IF(AD14>=70,"Yes","No"))
AD15: =IF(A15="","",MIN(100,MAX(0,70+SUMIF('Credibility Log'!$B:$B,A15,'Credibility Log'!$E:$E)))) | AE15: =IF(AD15="","",IFS(AD15>=90,"Level 5 - Ambassador",AD15>=80,"Level 4 - Competition Eligible",AD15>=70,"Level 3 - Trusted",AD15>=60,"Level 2 - Active",AD15>=50,"Level 1 - Watchlist",TRUE,"Level 0 - Restricted")) | AF15: =IF(AD15="","",IF(AD15>=70,"Yes","No"))
AD16: =IF(A16="","",MIN(100,MAX(0,70+SUMIF('Credibility Log'!$B:$B,A16,'Credibility Log'!$E:$E)))) | AE16: =IF(AD16="","",IFS(AD16>=90,"Level 5 - Ambassador",AD16>=80,"Level 4 - Competition Eligible",AD16>=70,"Level 3 - Trusted",AD16>=60,"Level 2 - Active",AD16>=50,"Level 1 - Watchlist",TRUE,"Level 0 - Restricted")) | AF16: =IF(AD16="","",IF(AD16>=70,"Yes","No"))
AD17: =IF(A17="","",MIN(100,MAX(0,70+SUMIF('Credibility Log'!$B:$B,A17,'Credibility Log'!$E:$E)))) | AE17: =IF(AD17="","",IFS(AD17>=90,"Level 5 - Ambassador",AD17>=80,"Level 4 - Competition Eligible",AD17>=70,"Level 3 - Trusted",AD17>=60,"Level 2 - Active",AD17>=50,"Level 1 - Watchlist",TRUE,"Level 0 - Restricted")) | AF17: =IF(AD17="","",IF(AD17>=70,"Yes","No"))
AD18: =IF(A18="","",MIN(100,MAX(0,70+SUMIF('Credibility Log'!$B:$B,A18,'Credibility Log'!$E:$E)))) | AE18: =IF(AD18="","",IFS(AD18>=90,"Level 5 - Ambassador",AD18>=80,"Level 4 - Competition Eligible",AD18>=70,"Level 3 - Trusted",AD18>=60,"Level 2 - Active",AD18>=50,"Level 1 - Watchlist",TRUE,"Level 0 - Restricted")) | AF18: =IF(AD18="","",IF(AD18>=70,"Yes","No"))
AD19: =IF(A19="","",MIN(100,MAX(0,70+SUMIF('Credibility Log'!$B:$B,A19,'Credibility Log'!$E:$E)))) | AE19: =IF(AD19="","",IFS(AD19>=90,"Level 5 - Ambassador",AD19>=80,"Level 4 - Competition Eligible",AD19>=70,"Level 3 - Trusted",AD19>=60,"Level 2 - Active",AD19>=50,"Level 1 - Watchlist",TRUE,"Level 0 - Restricted")) | AF19: =IF(AD19="","",IF(AD19>=70,"Yes","No"))
AD20: =IF(A20="","",MIN(100,MAX(0,70+SUMIF('Credibility Log'!$B:$B,A20,'Credibility Log'!$E:$E)))) | AE20: =IF(AD20="","",IFS(AD20>=90,"Level 5 - Ambassador",AD20>=80,"Level 4 - Competition Eligible",AD20>=70,"Level 3 - Trusted",AD20>=60,"Level 2 - Active",AD20>=50,"Level 1 - Watchlist",TRUE,"Level 0 - Restricted")) | AF20: =IF(AD20="","",IF(AD20>=70,"Yes","No"))
AD21: =IF(A21="","",MIN(100,MAX(0,70+SUMIF('Credibility Log'!$B:$B,A21,'Credibility Log'!$E:$E)))) | AE21: =IF(AD21="","",IFS(AD21>=90,"Level 5 - Ambassador",AD21>=80,"Level 4 - Competition Eligible",AD21>=70,"Level 3 - Trusted",AD21>=60,"Level 2 - Active",AD21>=50,"Level 1 - Watchlist",TRUE,"Level 0 - Restricted")) | AF21: =IF(AD21="","",IF(AD21>=70,"Yes","No"))
... AD200: =IF(A200="","",MIN(100,MAX(0,70+SUMIF('Credibility Log'!$B:$B,A200,'Credibility Log'!$E:$E)))) | AE200: =IF(AD200="","",IFS(AD200>=90,"Level 5 - Ambassador",AD200>=80,"Level 4 - Competition Eligible",AD200>=70,"Level 3 - Trusted",AD200>=60,"Level 2 - Active",AD200>=50,"Level 1 - Watchlist",TRUE,"Level 0 - Restricted")) | AF200: =IF(AD200="","",IF(AD200>=70,"Yes","No"))

Sheet Game Requests
A1: Game Requests
A2: Demand table: each row is a player wanting to start or join a game.
A4: Request_ID | B4: Player_ID | C4: Player Name | D4: Requested Game | E4: Game Category | F4: Preferred Location | G4: Max Travel Time (min) | H4: Preferred Date | I4: Time From | J4: Time To | K4: Required Players | L4: Skill Level | M4: Accepts Cost Split? | N4: Needs Approved Venue? | O4: Status | P4: Priority Score | Q4: Created At | R4: Last Updated | S4: Notes
A5: R001 | B5: P001 | C5: Ahmed Hassan | D5: Estimation | E5: Card/Social | F5: New Cairo | G5: 20 | H5: 46198 | I5: 8:00 PM | J5: 10:00 PM | K5: 4 | L5: Casual | M5: Yes | N5: Yes | O5: Open | P5: 100 | Q5: 46194 | R5: 46194 | S5: Need 4 players for Estimation
A6: R002 | B6: P004 | C6: Mona Adel | D6: Chess | E6: Board/Mind | F6: New Cairo | G6: 20 | H6: 46199 | I6: 6:00 PM | J6: 8:00 PM | K6: 2 | L6: Intermediate | M6: Yes | N6: Yes | O6: Open | P6: 100 | Q6: 46194 | R6: 46194 | S6: Looking for 1v1 chess
A7: R003 | B7: P005 | C7: Youssef Tarek | D7: Padel | E7: Sport | F7: Sheikh Zayed | G7: 15 | H7: 46200 | I7: 7:00 PM | J7: 8:30 PM | K7: 4 | L7: Beginner | M7: Yes | N7: Yes | O7: Matching | P7: 100 | Q7: 46194 | R7: 46194 | S7: Need players and court

Sheet Venues
A1: Venues
A2: Approved venue database. Do not send players unless agreement is signed and venue is approved.
A4: Venue_ID | B4: Venue Name | C4: Area | D4: Full Address | E4: Google Maps Link | F4: Venue Type | G4: Games Supported | H4: Opening Hours | I4: Contact Person | J4: Contact WhatsApp | K4: Cost Model | L4: Avg Cost | M4: Status | N4: Promotion Available? | O4: Commission Agreement? | P4: Terms Signed? | Q4: Subscription Tier | R4: Subscription Status | S4: Safety Notes | T4: Booking Rules | U4: Cancellation Rules | V4: Notes
A5: V001 | B5: Partner Café New Cairo | C5: New Cairo | D5: Placeholder address | E5: Paste Google Maps link | F5: Café | G5: Estimation, Chess, UNO | H5: 12 PM - 12 AM | I5: Owner Name | J5: +201011111111 | K5: Per table / minimum charge | L5: 300 | M5: Approved | N5: Yes | O5: To agree | P5: Yes | Q5: Basic | R5: Active | S5: Public place only | T5: Reservation required for groups | U5: Cancel 4 hours before | V5: Sample partner venue
A6: V002 | B6: Gaming Lounge Nasr City | C6: Nasr City | D6: Placeholder address | E6: Paste Google Maps link | F6: Gaming Lounge | G6: FIFA 2026, Call of Duty, League of Legends, Valorant | H6: 2 PM - 2 AM | I6: Owner Name | J6: +201022222222 | K6: Per hour / device | L6: 200 | M6: Pending | N6: Yes | O6: To agree | P6: No | Q6: Lead | R6: Pending | S6: Public place only | T6: Depends on setup availability | U6: Cancel 6 hours before | V6: Sample venue candidate
A7: V003 | B7: Padel Court Sheikh Zayed | C7: Sheikh Zayed | D7: Placeholder address | E7: Paste Google Maps link | F7: Padel Court | G7: Padel | H7: 8 AM - 12 AM | I7: Manager Name | J7: +201033333333 | K7: Per court / 90 min | L7: 800 | M7: Approved | N7: Yes | O7: To agree | P7: Yes | Q7: Competition Partner | R7: Active | S7: Approved public court | T7: Booking must be confirmed | U7: Cancel 8 hours before | V7: Sample partner venue
A8: V004 | B8: Billiards Hall Heliopolis | C8: Heliopolis | D8: Placeholder address | E8: Paste Google Maps link | F8: Billiards Hall | G8: Billiards | H8: 1 PM - 1 AM | I8: Manager Name | J8: +201044444444 | K8: Per hour / table | L8: 180 | M8: Pending | N8: No | O8: To agree | P8: No | Q8: Lead | R8: Pending | S8: Public venue | T8: Walk-in or reservation | U8: Cancel 4 hours before | V8: Sample venue candidate

Sheet Match Sessions
A1: Match Sessions
A2: Each proposed/confirmed game session. In MVP, admin approval is required before WhatsApp invitations.
A4: Match_ID | B4: Game | C4: Game Category | D4: Venue_ID | E4: Venue Name | F4: Area | G4: Game Date | H4: Start Time | I4: End Time | J4: Required Players | K4: Confirmed Players | L4: Players Needed | M4: Total Cost | N4: Discount % | O4: Cost After Discount | P4: Cost Per Player | Q4: Promotion_ID | R4: Notification Deadline | S4: Status | T4: Notes | U4: Captain_Player_ID | V4: Captain Name | W4: Minimum Credibility | X4: Dispute Status | Y4: Ranking Mode | Z4: Admin Approved? | AA4: Make Scenario Status
A5: M001 | B5: Estimation | C5: Card/Social | D5: V001 | E5: Partner Café New Cairo | F5: New Cairo | G5: 46198 | H5: 8:00 PM | I5: 10:00 PM | J5: 4 | K5: 3 | L5: =IF(A5="","",J5-K5) -> 1 | M5: 300 | N5: 0.1 | O5: =IF(A5="","",M5*(1-N5)) -> 270 | P5: =IF(A5="","",IF(J5=0,0,O5/J5)) -> 67.5 | Q5: PR001 | R5: Send at least 4 hours before 8:00 PM | S5: Open | T5: Needs 1 player | U5: P001 | V5: Ahmed Hassan | W5: 60 | X5: Clean | Y5: Ranked | Z5: Yes | AA5: Ready for invitation
A6: M002 | B6: Padel | C6: Sport | D6: V003 | E6: Padel Court Sheikh Zayed | F6: Sheikh Zayed | G6: 46200 | H6: 7:00 PM | I6: 8:30 PM | J6: 4 | K6: 0 | L6: =IF(A6="","",J6-K6) -> 4 | M6: 300 | N6: 0.1 | O6: =IF(A6="","",M6*(1-N6)) -> 270 | P6: =IF(A6="","",IF(J6=0,0,O6/J6)) -> 67.5 | Q6: PR002 | R6: Send at least 4 hours before 7:00 PM | S6: Pending Confirmation | T6: Sample padel match | U6: P005 | V6: Youssef Tarek | W6: 70 | X6: Clean | Y6: Ranked | Z6: No | AA6: Admin review
L7: =IF(A7="","",J7-K7) | M7: 300 | N7: 0.1 | O7: =IF(A7="","",M7*(1-N7)) | P7: =IF(A7="","",IF(J7=0,0,O7/J7))
L8: =IF(A8="","",J8-K8) | M8: 300 | N8: 0.1 | O8: =IF(A8="","",M8*(1-N8)) | P8: =IF(A8="","",IF(J8=0,0,O8/J8))
L9: =IF(A9="","",J9-K9) | M9: 300 | N9: 0.1 | O9: =IF(A9="","",M9*(1-N9)) | P9: =IF(A9="","",IF(J9=0,0,O9/J9))
L10: =IF(A10="","",J10-K10) | M10: 300 | N10: 0.1 | O10: =IF(A10="","",M10*(1-N10)) | P10: =IF(A10="","",IF(J10=0,0,O10/J10))
L11: =IF(A11="","",J11-K11) | M11: 300 | N11: 0.1 | O11: =IF(A11="","",M11*(1-N11)) | P11: =IF(A11="","",IF(J11=0,0,O11/J11))
L12: =IF(A12="","",J12-K12) | M12: 300 | N12: 0.1 | O12: =IF(A12="","",M12*(1-N12)) | P12: =IF(A12="","",IF(J12=0,0,O12/J12))
L13: =IF(A13="","",J13-K13) | M13: 300 | N13: 0.1 | O13: =IF(A13="","",M13*(1-N13)) | P13: =IF(A13="","",IF(J13=0,0,O13/J13))
L14: =IF(A14="","",J14-K14) | M14: 300 | N14: 0.1 | O14: =IF(A14="","",M14*(1-N14)) | P14: =IF(A14="","",IF(J14=0,0,O14/J14))
L15: =IF(A15="","",J15-K15) | M15: 300 | N15: 0.1 | O15: =IF(A15="","",M15*(1-N15)) | P15: =IF(A15="","",IF(J15=0,0,O15/J15))
L16: =IF(A16="","",J16-K16) | M16: 300 | N16: 0.1 | O16: =IF(A16="","",M16*(1-N16)) | P16: =IF(A16="","",IF(J16=0,0,O16/J16))
L17: =IF(A17="","",J17-K17) | M17: 300 | N17: 0.1 | O17: =IF(A17="","",M17*(1-N17)) | P17: =IF(A17="","",IF(J17=0,0,O17/J17))
L18: =IF(A18="","",J18-K18) | M18: 300 | N18: 0.1 | O18: =IF(A18="","",M18*(1-N18)) | P18: =IF(A18="","",IF(J18=0,0,O18/J18))
... L200: =IF(A200="","",J200-K200) | M200: 300 | N200: 0.1 | O200: =IF(A200="","",M200*(1-N200)) | P200: =IF(A200="","",IF(J200=0,0,O200/J200))

Sheet Confirmations
A1: Confirmations
A2: Tracks invitation responses and attendance.
A4: Confirmation_ID | B4: Match_ID | C4: Player_ID | D4: Player Name | E4: WhatsApp Number | F4: Invitation Sent? | G4: Invitation Time | H4: Response | I4: Confirmed? | J4: Attendance Status | K4: Cost Accepted? | L4: Reminder Sent? | M4: Notes
A5: C001 | B5: M001 | C5: P001 | D5: Ahmed Hassan | E5: +201000000001 | F5: Yes | G5: 46197.667 | H5: Accepted | I5: Yes | J5: Pending | K5: Yes | L5: No | M5: Sample
A6: C002 | B6: M001 | C6: P002 | D6: Omar Ali | E6: +201000000002 | F6: Yes | G6: 46197.667 | H6: Accepted | I6: Yes | J6: Pending | K6: Yes | L6: No | M6: Sample
A7: C003 | B7: M001 | C7: P003 | D7: Khaled Samir | E7: +201000000003 | F7: Yes | G7: 46197.667 | H7: No response | I7: No | J7: Pending | K7: Yes | L7: No | M7: Sample

Sheet Scores
A1: Scores
A2: Generic score sheet for all games. Estimation has a dedicated calculator too.
A4: Score_ID | B4: Match_ID | C4: Game | D4: Player_ID | E4: Player Name | F4: Team | G4: Score | H4: Winner? | I4: Submitted By | J4: Submitted At | K4: Verified? | L4: Verified By Captain? | M4: Dispute Status | N4: Notes
A5: S001 | B5: M001 | C5: Estimation | D5: P001 | E5: Ahmed Hassan | F5: Individual | G5: 0 | H5: No | I5: Manual sample | J5: 46198.938 | K5: No | L5: No | M5: Clean | N5: Fill after match

Sheet Ratings
A1: Ratings
A2: Post-game ratings feed credibility, venue performance, and incident detection.
A4: Rating_ID | B4: Rated_Player_ID | C4: Rated Player Name | D4: Match_ID | E4: Rated_By_Player_ID | F4: Rated By Name | G4: Overall Rating | H4: On Time Rating | I4: Respect Rating | J4: Fair Play Rating | K4: Skill Rating | L4: Would Play Again? | M4: Feedback | N4: Submitted At | O4: Dispute Status
A5: RT001 | B5: P001 | C5: Ahmed Hassan | D5: M001 | E5: P002 | F5: Omar Ali | G5: 5 | H5: 5 | I5: 5 | J5: 5 | K5: 4 | L5: Yes | M5: Sample rating | N5: 46198.958 | O5: None

Sheet Promotions
A1: Promotions
A2: Promotions and discounts agreed with approved venues.
A4: Promotion_ID | B4: Venue_ID | C4: Venue Name | D4: Game | E4: Area | F4: Discount Type | G4: Discount Value | H4: Start Date | I4: End Date | J4: Terms | K4: Status | L4: Usage Count | M4: Notes
A5: PR001 | B5: V001 | C5: Partner Café New Cairo | D5: Estimation | E5: New Cairo | F5: Percent | G5: 0.1 | H5: 46194 | I5: 46224 | J5: Platform players only | K5: Active | L5: 0 | M5: Sample
A6: PR002 | B6: V003 | C6: Padel Court Sheikh Zayed | D6: Padel | E6: Sheikh Zayed | F6: Percent | G6: 0.15 | H6: 46194 | I6: 46224 | J6: Off-peak hours only | K6: Active | L6: 0 | M6: Sample

Sheet Competitions
A1: Competitions
A2: Area competitions with prizes/promotions, not betting.
A4: Competition_ID | B4: Name | C4: Game | D4: Area | E4: Venue_ID | F4: Venue Name | G4: Start Date | H4: End Date | I4: Entry Rules | J4: Prize Type | K4: Prize Value | L4: Sponsor | M4: Status | N4: Leaderboard_ID | O4: Notes
A5: CMP001 | B5: New Cairo FIFA Cup | C5: FIFA 2026 | D5: New Cairo | E5: V002 | F5: Gaming Lounge Nasr City | G5: 46204 | H5: 46210 | I5: Min credibility 70 | J5: Cash/Promotion | K5: 2000 | L5: To find | M5: Planning | N5: LB_COMP_001 | O5: Prize is official competition reward, not betting

Sheet Scoring Rules
A1: Scoring Rules
A2: Configuration for credibility, rankings, and Estimation scoring.
A4: Action Type | B4: Score Change | C4: When It Happens | D4: Auto/Admin | E4: Notes | G4: Ranking Event | H4: Points | I4: Applies To | J4: Notes
A5: Verified profile | B5: 5 | C5: Phone/profile verified | D5: Auto/Admin | E5: Reduce fake profiles | G5: Participation | H5: 1 | I5: All ranked games | J5: Encourages activity
A6: Completed game | B6: 2 | C6: Player attended and game completed | D6: Auto | E6: After match completion | G6: Win | H6: 3 | I6: Competitive games | J6: Core ranking unit
A7: High rating | B7: 3 | C7: Average post-game rating is 4.5+ | D7: Auto | E7: Based on ratings | G7: Draw | H7: 1 | I7: Games with draw | J7: Optional
A8: On-time attendance | B8: 2 | C8: Player attends on time | D8: Auto/Captain | E8: Captain/venue confirmation | G8: Loss | H8: 0 | I8: Competitive games | J8: No negative ranking points
A9: Early cancellation | B9: 0 | C9: Cancellation before allowed window | D9: Auto | E9: No penalty | G9: Tournament winner | H9: 10 | I9: Competitions | J9: Official competition bonus
A10: Late cancellation | B10: -5 | C10: Cancellation after allowed window | D10: Auto/Admin | E10: Can be adjusted | G10: Runner-up | H10: 5 | I10: Competitions | J10: Official competition bonus
A11: No-show | B11: -15 | C11: Confirmed but did not attend | D11: Admin/Captain | E11: Major penalty | G11: Fair play bonus | H11: 2 | I11: Admin/captain approved | J11: Community incentive
A12: Fake information | B12: -20 | C12: Wrong identity/location/game data | D12: Admin | E12: Manual review
A13: Confirmed complaint | B13: -10 | C13: Valid minor complaint | D13: Admin | E13: Severity based
A14: Serious harassment | B14: Suspend/Ban | C14: Confirmed serious report | D14: Admin only | E14: Never fully AI automated
A18: Setting | B18: MVP Value | C18: Editable? | D18: Notes | G18: Action | H18: Minimum Credibility | I18: Rule
A19: Correct estimate bonus | B19: 10 | C19: Yes | D19: When estimate equals actual result | G19: Join normal game | H19: 50 | I19: Below this, admin approval required
A20: Add estimate value if correct | B20: Yes | C20: Yes | D20: Score = bonus + estimate | G20: Join competition | H20: 70 | I20: Protects competition quality
A21: Wrong estimate penalty multiplier | B21: 1 | C21: Yes | D21: Penalty = absolute difference × multiplier | G21: Become match captain | H21: 80 | I21: Captain must be reliable
A22: Zero estimate special rule | B22: No | C22: Yes | D22: Can be activated later | G22: Appear on public leaderboard | H22: 60 | I22: Avoid promoting risky players
A23: Winner condition | B23: Highest total score | C23: Yes | D23: Standard condition | G23: Become ambassador | H23: 90 | I23: Trusted community role
A24: Rounds per match | B24: Configurable | C24: Yes | D24: Depends on agreed rules

Sheet Credibility Log
A1: Credibility Score Log
A2: Every credibility score change is logged. Players score = 70 + SUM of changes.
A4: Log_ID | B4: Player_ID | C4: Player Name | D4: Match_ID | E4: Score Change | F4: Action Type | G4: Reason | H4: Auto/Admin | I4: Admin Approved? | J4: Date | K4: Notes
A5: CL001 | B5: P001 | C5: Ahmed Hassan | D5: M001 | E5: 5 | F5: Verified profile | G5: Initial MVP verification | H5: Admin | I5: Yes | J5: 46194 | K5: Sample
A6: CL002 | B6: P001 | C6: Ahmed Hassan | D6: M001 | E6: 2 | F6: Completed game | G6: Attended sample Estimation match | H6: Auto | I6: Yes | J6: 46195 | K6: Sample
A7: CL003 | B7: P002 | C7: Omar Ali | D7: M001 | E7: 5 | F7: Verified profile | G7: Phone verified | H7: Admin | I7: Yes | J7: 46194 | K7: Sample
A8: CL004 | B8: P003 | C8: Khaled Samir | D8: M001 | E8: -15 | F8: No-show | G8: Confirmed but did not attend | H8: Admin | I8: Yes | J8: 46195 | K8: Sample penalty

Sheet Player Rankings
A1: Player Rankings
A2: Ranking = performance. Credibility = trust filter. Keep them separate.
A4: Ranking_ID | B4: Player_ID | C4: Player Name | D4: Game | E4: Area | F4: Period | G4: Games Played | H4: Wins | I4: Draws | J4: Losses | K4: Participation Points | L4: Win Points | M4: Draw Points | N4: Competition Bonus | O4: Fair Play Bonus | P4: Total Ranking Points | Q4: Win Rate | R4: Rank | S4: Eligibility | T4: Notes
A5: RK001 | B5: P001 | C5: Ahmed Hassan | D5: Estimation | E5: New Cairo | F5: Jun 2026 | G5: 3 | H5: 2 | I5: 0 | J5: 1 | K5: =IF(A5="","",G5*1) -> 3 | L5: =IF(A5="","",H5*3) -> 6 | M5: =IF(A5="","",I5*1) -> 0 | N5: 0 | O5: 2 | P5: =IF(A5="","",K5+L5+M5+N5+O5) -> 11 | Q5: =IF(A5="","",IF(G5=0,0,H5/G5)) -> 0.66666667 | R5: =IF(A5="","",1+COUNTIF($P$5:$P$200,">"&P5)) -> 2 | S5: =IF(A5="","",IF(VLOOKUP(B5,Players!$A:$AF,30,FALSE)>=60,"Visible","Hidden/Review")) -> Visible | T5: Sample
A6: RK002 | B6: P002 | C6: Omar Ali | D6: FIFA 2026 | E6: New Cairo | F6: Jun 2026 | G6: 4 | H6: 3 | I6: 0 | J6: 1 | K6: =IF(A6="","",G6*1) -> 4 | L6: =IF(A6="","",H6*3) -> 9 | M6: =IF(A6="","",I6*1) -> 0 | N6: 0 | O6: 2 | P6: =IF(A6="","",K6+L6+M6+N6+O6) -> 15 | Q6: =IF(A6="","",IF(G6=0,0,H6/G6)) -> 0.75 | R6: =IF(A6="","",1+COUNTIF($P$5:$P$200,">"&P6)) -> 1 | S6: =IF(A6="","",IF(VLOOKUP(B6,Players!$A:$AF,30,FALSE)>=60,"Visible","Hidden/Review")) -> Visible | T6: Sample
A7: RK003 | B7: P004 | C7: Mona Adel | D7: Chess | E7: New Cairo | F7: Jun 2026 | G7: 2 | H7: 1 | I7: 1 | J7: 0 | K7: =IF(A7="","",G7*1) -> 2 | L7: =IF(A7="","",H7*3) -> 3 | M7: =IF(A7="","",I7*1) -> 1 | N7: 0 | O7: 2 | P7: =IF(A7="","",K7+L7+M7+N7+O7) -> 8 | Q7: =IF(A7="","",IF(G7=0,0,H7/G7)) -> 0.5 | R7: =IF(A7="","",1+COUNTIF($P$5:$P$200,">"&P7)) -> 3 | S7: =IF(A7="","",IF(VLOOKUP(B7,Players!$A:$AF,30,FALSE)>=60,"Visible","Hidden/Review")) -> Visible | T7: Sample
A8: RK004 | B8: P005 | C8: Youssef Tarek | D8: Padel | E8: Sheikh Zayed | F8: Jun 2026 | G8: 1 | H8: 0 | I8: 0 | J8: 1 | K8: =IF(A8="","",G8*1) -> 1 | L8: =IF(A8="","",H8*3) -> 0 | M8: =IF(A8="","",I8*1) -> 0 | N8: 0 | O8: 2 | P8: =IF(A8="","",K8+L8+M8+N8+O8) -> 3 | Q8: =IF(A8="","",IF(G8=0,0,H8/G8)) -> 0 | R8: =IF(A8="","",1+COUNTIF($P$5:$P$200,">"&P8)) -> 4 | S8: =IF(A8="","",IF(VLOOKUP(B8,Players!$A:$AF,30,FALSE)>=60,"Visible","Hidden/Review")) -> Visible | T8: Sample
K9: =IF(A9="","",G9*1) | L9: =IF(A9="","",H9*3) | M9: =IF(A9="","",I9*1) | N9: 0 | O9: 2 | P9: =IF(A9="","",K9+L9+M9+N9+O9) | Q9: =IF(A9="","",IF(G9=0,0,H9/G9)) | R9: =IF(A9="","",1+COUNTIF($P$5:$P$200,">"&P9)) | S9: =IF(A9="","",IF(VLOOKUP(B9,Players!$A:$AF,30,FALSE)>=60,"Visible","Hidden/Review"))
K10: =IF(A10="","",G10*1) | L10: =IF(A10="","",H10*3) | M10: =IF(A10="","",I10*1) | N10: 0 | O10: 2 | P10: =IF(A10="","",K10+L10+M10+N10+O10) | Q10: =IF(A10="","",IF(G10=0,0,H10/G10)) | R10: =IF(A10="","",1+COUNTIF($P$5:$P$200,">"&P10)) | S10: =IF(A10="","",IF(VLOOKUP(B10,Players!$A:$AF,30,FALSE)>=60,"Visible","Hidden/Review"))
K11: =IF(A11="","",G11*1) | L11: =IF(A11="","",H11*3) | M11: =IF(A11="","",I11*1) | N11: 0 | O11: 2 | P11: =IF(A11="","",K11+L11+M11+N11+O11) | Q11: =IF(A11="","",IF(G11=0,0,H11/G11)) | R11: =IF(A11="","",1+COUNTIF($P$5:$P$200,">"&P11)) | S11: =IF(A11="","",IF(VLOOKUP(B11,Players!$A:$AF,30,FALSE)>=60,"Visible","Hidden/Review"))
K12: =IF(A12="","",G12*1) | L12: =IF(A12="","",H12*3) | M12: =IF(A12="","",I12*1) | N12: 0 | O12: 2 | P12: =IF(A12="","",K12+L12+M12+N12+O12) | Q12: =IF(A12="","",IF(G12=0,0,H12/G12)) | R12: =IF(A12="","",1+COUNTIF($P$5:$P$200,">"&P12)) | S12: =IF(A12="","",IF(VLOOKUP(B12,Players!$A:$AF,30,FALSE)>=60,"Visible","Hidden/Review"))
K13: =IF(A13="","",G13*1) | L13: =IF(A13="","",H13*3) | M13: =IF(A13="","",I13*1) | N13: 0 | O13: 2 | P13: =IF(A13="","",K13+L13+M13+N13+O13) | Q13: =IF(A13="","",IF(G13=0,0,H13/G13)) | R13: =IF(A13="","",1+COUNTIF($P$5:$P$200,">"&P13)) | S13: =IF(A13="","",IF(VLOOKUP(B13,Players!$A:$AF,30,FALSE)>=60,"Visible","Hidden/Review"))
K14: =IF(A14="","",G14*1) | L14: =IF(A14="","",H14*3) | M14: =IF(A14="","",I14*1) | N14: 0 | O14: 2 | P14: =IF(A14="","",K14+L14+M14+N14+O14) | Q14: =IF(A14="","",IF(G14=0,0,H14/G14)) | R14: =IF(A14="","",1+COUNTIF($P$5:$P$200,">"&P14)) | S14: =IF(A14="","",IF(VLOOKUP(B14,Players!$A:$AF,30,FALSE)>=60,"Visible","Hidden/Review"))
K15: =IF(A15="","",G15*1) | L15: =IF(A15="","",H15*3) | M15: =IF(A15="","",I15*1) | N15: 0 | O15: 2 | P15: =IF(A15="","",K15+L15+M15+N15+O15) | Q15: =IF(A15="","",IF(G15=0,0,H15/G15)) | R15: =IF(A15="","",1+COUNTIF($P$5:$P$200,">"&P15)) | S15: =IF(A15="","",IF(VLOOKUP(B15,Players!$A:$AF,30,FALSE)>=60,"Visible","Hidden/Review"))
K16: =IF(A16="","",G16*1) | L16: =IF(A16="","",H16*3) | M16: =IF(A16="","",I16*1) | N16: 0 | O16: 2 | P16: =IF(A16="","",K16+L16+M16+N16+O16) | Q16: =IF(A16="","",IF(G16=0,0,H16/G16)) | R16: =IF(A16="","",1+COUNTIF($P$5:$P$200,">"&P16)) | S16: =IF(A16="","",IF(VLOOKUP(B16,Players!$A:$AF,30,FALSE)>=60,"Visible","Hidden/Review"))
K17: =IF(A17="","",G17*1) | L17: =IF(A17="","",H17*3) | M17: =IF(A17="","",I17*1) | N17: 0 | O17: 2 | P17: =IF(A17="","",K17+L17+M17+N17+O17) | Q17: =IF(A17="","",IF(G17=0,0,H17/G17)) | R17: =IF(A17="","",1+COUNTIF($P$5:$P$200,">"&P17)) | S17: =IF(A17="","",IF(VLOOKUP(B17,Players!$A:$AF,30,FALSE)>=60,"Visible","Hidden/Review"))
K18: =IF(A18="","",G18*1) | L18: =IF(A18="","",H18*3) | M18: =IF(A18="","",I18*1) | N18: 0 | O18: 2 | P18: =IF(A18="","",K18+L18+M18+N18+O18) | Q18: =IF(A18="","",IF(G18=0,0,H18/G18)) | R18: =IF(A18="","",1+COUNTIF($P$5:$P$200,">"&P18)) | S18: =IF(A18="","",IF(VLOOKUP(B18,Players!$A:$AF,30,FALSE)>=60,"Visible","Hidden/Review"))
K19: =IF(A19="","",G19*1) | L19: =IF(A19="","",H19*3) | M19: =IF(A19="","",I19*1) | N19: 0 | O19: 2 | P19: =IF(A19="","",K19+L19+M19+N19+O19) | Q19: =IF(A19="","",IF(G19=0,0,H19/G19)) | R19: =IF(A19="","",1+COUNTIF($P$5:$P$200,">"&P19)) | S19: =IF(A19="","",IF(VLOOKUP(B19,Players!$A:$AF,30,FALSE)>=60,"Visible","Hidden/Review"))
K20: =IF(A20="","",G20*1) | L20: =IF(A20="","",H20*3) | M20: =IF(A20="","",I20*1) | N20: 0 | O20: 2 | P20: =IF(A20="","",K20+L20+M20+N20+O20) | Q20: =IF(A20="","",IF(G20=0,0,H20/G20)) | R20: =IF(A20="","",1+COUNTIF($P$5:$P$200,">"&P20)) | S20: =IF(A20="","",IF(VLOOKUP(B20,Players!$A:$AF,30,FALSE)>=60,"Visible","Hidden/Review"))
... K200: =IF(A200="","",G200*1) | L200: =IF(A200="","",H200*3) | M200: =IF(A200="","",I200*1) | N200: 0 | O200: 2 | P200: =IF(A200="","",K200+L200+M200+N200+O200) | Q200: =IF(A200="","",IF(G200=0,0,H200/G200)) | R200: =IF(A200="","",1+COUNTIF($P$5:$P$200,">"&P200)) | S200: =IF(A200="","",IF(VLOOKUP(B200,Players!$A:$AF,30,FALSE)>=60,"Visible","Hidden/Review"))

Sheet Estimation Calculator
A1: Estimation Calculator
A2: MVP calculator for Estimation scores. Rules remain configurable.
A4: Game_ID | B4: Round # | C4: Player_ID | D4: Player Name | E4: Estimate/Bid | F4: Actual Result | G4: Difference | H4: Correct? | I4: Round Score | J4: Running Total | K4: Winner After Round? | L4: Notes
A5: M001 | B5: 1 | C5: P001 | D5: Ahmed Hassan | E5: 3 | F5: 3 | G5: =IF(A5="","",ABS(E5-F5)) -> 0 | H5: =IF(A5="","",IF(E5=F5,"Yes","No")) -> Yes | I5: =IF(A5="","",IF(H5="Yes",10+E5,-G5*1)) -> 13 | J5: =IF(A5="","",SUMIFS($I$5:I5,$C$5:C5,C5,$A$5:A5,A5)) -> 13 | K5: =IF(A5="","",IF(J5=MAXIFS($J$5:$J$200,$A$5:$A$200,A5,$B$5:$B$200,B5),"Yes","No")) -> #NAME? | L5: Correct estimate sample
A6: M001 | B6: 1 | C6: P002 | D6: Omar Ali | E6: 2 | F6: 3 | G6: =IF(A6="","",ABS(E6-F6)) -> 1 | H6: =IF(A6="","",IF(E6=F6,"Yes","No")) -> No | I6: =IF(A6="","",IF(H6="Yes",10+E6,-G6*1)) -> -1 | J6: =IF(A6="","",SUMIFS($I$5:I6,$C$5:C6,C6,$A$5:A6,A6)) -> -1 | K6: =IF(A6="","",IF(J6=MAXIFS($J$5:$J$200,$A$5:$A$200,A6,$B$5:$B$200,B6),"Yes","No")) -> #NAME? | L6: Wrong estimate sample
A7: M001 | B7: 1 | C7: P003 | D7: Khaled Samir | E7: 4 | F7: 3 | G7: =IF(A7="","",ABS(E7-F7)) -> 1 | H7: =IF(A7="","",IF(E7=F7,"Yes","No")) -> No | I7: =IF(A7="","",IF(H7="Yes",10+E7,-G7*1)) -> -1 | J7: =IF(A7="","",SUMIFS($I$5:I7,$C$5:C7,C7,$A$5:A7,A7)) -> -1 | K7: =IF(A7="","",IF(J7=MAXIFS($J$5:$J$200,$A$5:$A$200,A7,$B$5:$B$200,B7),"Yes","No")) -> #NAME? | L7: Wrong estimate sample
A8: M001 | B8: 1 | C8: P004 | D8: Mona Adel | E8: 1 | F8: 1 | G8: =IF(A8="","",ABS(E8-F8)) -> 0 | H8: =IF(A8="","",IF(E8=F8,"Yes","No")) -> Yes | I8: =IF(A8="","",IF(H8="Yes",10+E8,-G8*1)) -> 11 | J8: =IF(A8="","",SUMIFS($I$5:I8,$C$5:C8,C8,$A$5:A8,A8)) -> 11 | K8: =IF(A8="","",IF(J8=MAXIFS($J$5:$J$200,$A$5:$A$200,A8,$B$5:$B$200,B8),"Yes","No")) -> #NAME? | L8: Correct estimate sample
A9: M001 | B9: 2 | C9: P001 | D9: Ahmed Hassan | E9: 2 | F9: 1 | G9: =IF(A9="","",ABS(E9-F9)) -> 1 | H9: =IF(A9="","",IF(E9=F9,"Yes","No")) -> No | I9: =IF(A9="","",IF(H9="Yes",10+E9,-G9*1)) -> -1 | J9: =IF(A9="","",SUMIFS($I$5:I9,$C$5:C9,C9,$A$5:A9,A9)) -> 12 | K9: =IF(A9="","",IF(J9=MAXIFS($J$5:$J$200,$A$5:$A$200,A9,$B$5:$B$200,B9),"Yes","No")) -> #NAME?
A10: M001 | B10: 2 | C10: P002 | D10: Omar Ali | E10: 1 | F10: 1 | G10: =IF(A10="","",ABS(E10-F10)) -> 0 | H10: =IF(A10="","",IF(E10=F10,"Yes","No")) -> Yes | I10: =IF(A10="","",IF(H10="Yes",10+E10,-G10*1)) -> 11 | J10: =IF(A10="","",SUMIFS($I$5:I10,$C$5:C10,C10,$A$5:A10,A10)) -> 10 | K10: =IF(A10="","",IF(J10=MAXIFS($J$5:$J$200,$A$5:$A$200,A10,$B$5:$B$200,B10),"Yes","No")) -> #NAME?
A11: M001 | B11: 2 | C11: P003 | D11: Khaled Samir | E11: 3 | F11: 1 | G11: =IF(A11="","",ABS(E11-F11)) -> 2 | H11: =IF(A11="","",IF(E11=F11,"Yes","No")) -> No | I11: =IF(A11="","",IF(H11="Yes",10+E11,-G11*1)) -> -2 | J11: =IF(A11="","",SUMIFS($I$5:I11,$C$5:C11,C11,$A$5:A11,A11)) -> -3 | K11: =IF(A11="","",IF(J11=MAXIFS($J$5:$J$200,$A$5:$A$200,A11,$B$5:$B$200,B11),"Yes","No")) -> #NAME?
A12: M001 | B12: 2 | C12: P004 | D12: Mona Adel | E12: 1 | F12: 1 | G12: =IF(A12="","",ABS(E12-F12)) -> 0 | H12: =IF(A12="","",IF(E12=F12,"Yes","No")) -> Yes | I12: =IF(A12="","",IF(H12="Yes",10+E12,-G12*1)) -> 11 | J12: =IF(A12="","",SUMIFS($I$5:I12,$C$5:C12,C12,$A$5:A12,A12)) -> 22 | K12: =IF(A12="","",IF(J12=MAXIFS($J$5:$J$200,$A$5:$A$200,A12,$B$5:$B$200,B12),"Yes","No")) -> #NAME?
G13: =IF(A13="","",ABS(E13-F13)) | H13: =IF(A13="","",IF(E13=F13,"Yes","No")) | I13: =IF(A13="","",IF(H13="Yes",10+E13,-G13*1)) | J13: =IF(A13="","",SUMIFS($I$5:I13,$C$5:C13,C13,$A$5:A13,A13)) | K13: =IF(A13="","",IF(J13=MAXIFS($J$5:$J$200,$A$5:$A$200,A13,$B$5:$B$200,B13),"Yes","No"))
G14: =IF(A14="","",ABS(E14-F14)) | H14: =IF(A14="","",IF(E14=F14,"Yes","No")) | I14: =IF(A14="","",IF(H14="Yes",10+E14,-G14*1)) | J14: =IF(A14="","",SUMIFS($I$5:I14,$C$5:C14,C14,$A$5:A14,A14)) | K14: =IF(A14="","",IF(J14=MAXIFS($J$5:$J$200,$A$5:$A$200,A14,$B$5:$B$200,B14),"Yes","No"))
G15: =IF(A15="","",ABS(E15-F15)) | H15: =IF(A15="","",IF(E15=F15,"Yes","No")) | I15: =IF(A15="","",IF(H15="Yes",10+E15,-G15*1)) | J15: =IF(A15="","",SUMIFS($I$5:I15,$C$5:C15,C15,$A$5:A15,A15)) | K15: =IF(A15="","",IF(J15=MAXIFS($J$5:$J$200,$A$5:$A$200,A15,$B$5:$B$200,B15),"Yes","No"))
G16: =IF(A16="","",ABS(E16-F16)) | H16: =IF(A16="","",IF(E16=F16,"Yes","No")) | I16: =IF(A16="","",IF(H16="Yes",10+E16,-G16*1)) | J16: =IF(A16="","",SUMIFS($I$5:I16,$C$5:C16,C16,$A$5:A16,A16)) | K16: =IF(A16="","",IF(J16=MAXIFS($J$5:$J$200,$A$5:$A$200,A16,$B$5:$B$200,B16),"Yes","No"))
G17: =IF(A17="","",ABS(E17-F17)) | H17: =IF(A17="","",IF(E17=F17,"Yes","No")) | I17: =IF(A17="","",IF(H17="Yes",10+E17,-G17*1)) | J17: =IF(A17="","",SUMIFS($I$5:I17,$C$5:C17,C17,$A$5:A17,A17)) | K17: =IF(A17="","",IF(J17=MAXIFS($J$5:$J$200,$A$5:$A$200,A17,$B$5:$B$200,B17),"Yes","No"))
G18: =IF(A18="","",ABS(E18-F18)) | H18: =IF(A18="","",IF(E18=F18,"Yes","No")) | I18: =IF(A18="","",IF(H18="Yes",10+E18,-G18*1)) | J18: =IF(A18="","",SUMIFS($I$5:I18,$C$5:C18,C18,$A$5:A18,A18)) | K18: =IF(A18="","",IF(J18=MAXIFS($J$5:$J$200,$A$5:$A$200,A18,$B$5:$B$200,B18),"Yes","No"))
G19: =IF(A19="","",ABS(E19-F19)) | H19: =IF(A19="","",IF(E19=F19,"Yes","No")) | I19: =IF(A19="","",IF(H19="Yes",10+E19,-G19*1)) | J19: =IF(A19="","",SUMIFS($I$5:I19,$C$5:C19,C19,$A$5:A19,A19)) | K19: =IF(A19="","",IF(J19=MAXIFS($J$5:$J$200,$A$5:$A$200,A19,$B$5:$B$200,B19),"Yes","No"))
G20: =IF(A20="","",ABS(E20-F20)) | H20: =IF(A20="","",IF(E20=F20,"Yes","No")) | I20: =IF(A20="","",IF(H20="Yes",10+E20,-G20*1)) | J20: =IF(A20="","",SUMIFS($I$5:I20,$C$5:C20,C20,$A$5:A20,A20)) | K20: =IF(A20="","",IF(J20=MAXIFS($J$5:$J$200,$A$5:$A$200,A20,$B$5:$B$200,B20),"Yes","No"))
G21: =IF(A21="","",ABS(E21-F21)) | H21: =IF(A21="","",IF(E21=F21,"Yes","No")) | I21: =IF(A21="","",IF(H21="Yes",10+E21,-G21*1)) | J21: =IF(A21="","",SUMIFS($I$5:I21,$C$5:C21,C21,$A$5:A21,A21)) | K21: =IF(A21="","",IF(J21=MAXIFS($J$5:$J$200,$A$5:$A$200,A21,$B$5:$B$200,B21),"Yes","No"))
G22: =IF(A22="","",ABS(E22-F22)) | H22: =IF(A22="","",IF(E22=F22,"Yes","No")) | I22: =IF(A22="","",IF(H22="Yes",10+E22,-G22*1)) | J22: =IF(A22="","",SUMIFS($I$5:I22,$C$5:C22,C22,$A$5:A22,A22)) | K22: =IF(A22="","",IF(J22=MAXIFS($J$5:$J$200,$A$5:$A$200,A22,$B$5:$B$200,B22),"Yes","No"))
G23: =IF(A23="","",ABS(E23-F23)) | H23: =IF(A23="","",IF(E23=F23,"Yes","No")) | I23: =IF(A23="","",IF(H23="Yes",10+E23,-G23*1)) | J23: =IF(A23="","",SUMIFS($I$5:I23,$C$5:C23,C23,$A$5:A23,A23)) | K23: =IF(A23="","",IF(J23=MAXIFS($J$5:$J$200,$A$5:$A$200,A23,$B$5:$B$200,B23),"Yes","No"))
G24: =IF(A24="","",ABS(E24-F24)) | H24: =IF(A24="","",IF(E24=F24,"Yes","No")) | I24: =IF(A24="","",IF(H24="Yes",10+E24,-G24*1)) | J24: =IF(A24="","",SUMIFS($I$5:I24,$C$5:C24,C24,$A$5:A24,A24)) | K24: =IF(A24="","",IF(J24=MAXIFS($J$5:$J$200,$A$5:$A$200,A24,$B$5:$B$200,B24),"Yes","No"))
... G200: =IF(A200="","",ABS(E200-F200)) | H200: =IF(A200="","",IF(E200=F200,"Yes","No")) | I200: =IF(A200="","",IF(H200="Yes",10+E200,-G200*1)) | J200: =IF(A200="","",SUMIFS($I$5:I200,$C$5:C200,C200,$A$5:A200,A200)) | K200: =IF(A200="","",IF(J200=MAXIFS($J$5:$J$200,$A$5:$A$200,A200,$B$5:$B$200,B200),"Yes","No"))

Sheet Leaderboards
A1: Leaderboards
A2: Leaderboards by player, team, area, venue, and competition.
A4: Leaderboard_ID | B4: Type | C4: Game | D4: Area | E4: Period | F4: Entity_ID | G4: Entity Name | H4: Games/Events | I4: Points | J4: Credibility Filter | K4: Rank | L4: Visibility | M4: Last Updated | N4: Notes
A5: LB001 | B5: Player | C5: Estimation | D5: New Cairo | E5: Jun 2026 | F5: P001 | G5: Ahmed Hassan | H5: 3 | I5: 25 | J5: 60 | K5: =IF(A5="","",RANK(I5,$I$5:$I$200,0)) -> 4 | L5: Public | M5: 46194 | N5: Sample
A6: LB002 | B6: Player | C6: FIFA 2026 | D6: New Cairo | E6: Jun 2026 | F6: P002 | G6: Omar Ali | H6: 4 | I6: 30 | J6: 60 | K6: =IF(A6="","",RANK(I6,$I$5:$I$200,0)) -> 3 | L6: Public | M6: 46194 | N6: Sample
A7: LB003 | B7: Area | C7: All | D7: New Cairo | E7: Jun 2026 | F7: AREA001 | G7: New Cairo | H7: 12 | I7: 120 | K7: =IF(A7="","",RANK(I7,$I$5:$I$200,0)) -> 1 | L7: Public | M7: 46194 | N7: Area activity
A8: LB004 | B8: Venue | C8: All | D8: New Cairo | E8: Jun 2026 | F8: V001 | G8: Partner Café New Cairo | H8: 8 | I8: 80 | K8: =IF(A8="","",RANK(I8,$I$5:$I$200,0)) -> 2 | L8: Internal/Public | M8: 46194 | N8: Venue leaderboard
K9: =IF(A9="","",RANK(I9,$I$5:$I$200,0))
K10: =IF(A10="","",RANK(I10,$I$5:$I$200,0))
K11: =IF(A11="","",RANK(I11,$I$5:$I$200,0))
K12: =IF(A12="","",RANK(I12,$I$5:$I$200,0))
K13: =IF(A13="","",RANK(I13,$I$5:$I$200,0))
K14: =IF(A14="","",RANK(I14,$I$5:$I$200,0))
K15: =IF(A15="","",RANK(I15,$I$5:$I$200,0))
K16: =IF(A16="","",RANK(I16,$I$5:$I$200,0))
K17: =IF(A17="","",RANK(I17,$I$5:$I$200,0))
K18: =IF(A18="","",RANK(I18,$I$5:$I$200,0))
K19: =IF(A19="","",RANK(I19,$I$5:$I$200,0))
K20: =IF(A20="","",RANK(I20,$I$5:$I$200,0))
... K200: =IF(A200="","",RANK(I200,$I$5:$I$200,0))

Sheet Venue Performance
A1: Venue Performance
A2: Monthly venue reporting and subscription value proof.
A4: Venue_ID | B4: Venue Name | C4: Area | D4: Period | E4: Subscription Tier | F4: Subscription Status | G4: Games Hosted | H4: Players Sent | I4: Estimated Venue Revenue | J4: Promo Uses | K4: Average Venue Rating | L4: Complaint Count | M4: Renewal Date | N4: Upsell Opportunity | O4: Notes
A5: V001 | B5: Partner Café New Cairo | C5: New Cairo | D5: Jun 2026 | E5: Basic | F5: Active | G5: 8 | H5: 32 | I5: 2400 | J5: 10 | K5: 4.7 | L5: 0 | M5: 46224 | N5: Featured tier | O5: Sample
A6: V003 | B6: Padel Court Sheikh Zayed | C6: Sheikh Zayed | D6: Jun 2026 | E6: Competition Partner | F6: Active | G6: 4 | H6: 16 | I6: 3200 | J6: 6 | K6: 4.5 | L6: 1 | M6: 46224 | N6: Area tournament | O6: Sample
A7: V002 | B7: Gaming Lounge Nasr City | C7: Nasr City | D7: Jun 2026 | E7: Lead | F7: Pending | G7: 0 | H7: 0 | I7: 0 | J7: 0 | L7: 0 | N7: Needs contract | O7: Sample

Sheet Reports & Incidents
A1: Reports & Incidents
A2: Harassment, safety, no-show, cheating, cost dispute, and venue reports. Serious cases require manual review.
A4: Incident_ID | B4: Reporter_Player_ID | C4: Reporter Name | D4: Reported_Player_ID | E4: Reported Name | F4: Match_ID | G4: Venue_ID | H4: Incident Type | I4: Severity | J4: Description | K4: Evidence Link | L4: Status | M4: Admin Owner | N4: Decision | O4: Action Taken | P4: Date Opened | Q4: Date Closed | R4: Notes
A5: IN001 | B5: P002 | C5: Omar Ali | D5: P003 | E5: Khaled Samir | F5: M001 | G5: V001 | H5: No-show | I5: Medium | J5: Player confirmed but did not attend. | L5: Under review | M5: Marwan | P5: 46195 | R5: Sample
A6: IN002 | B6: P004 | C6: Mona Adel | F6: M002 | G6: V003 | H6: Venue complaint | I6: Low | J6: Delay in court start time. | L6: New | M6: Abdelrahman | P6: 46195 | R6: Sample

Sheet Verification Levels
A1: Verification Levels
A2: Player maturity levels and permissions.
A4: Level | B4: Name | C4: Requirement | D4: Allowed Actions | E4: Restrictions | F4: Minimum Credibility
A5: 0 | B5: Restricted/New | C5: Incomplete profile or credibility below 50 | D5: Cannot auto-join; admin review needed | E5: No competitions, no captain role | F5: 0
A6: 1 | B6: Watchlist | C6: Credibility 50–59 | D6: May join normal games with admin approval | E6: No competitions | F6: 50
A7: 2 | B7: Active | C7: Credibility 60–69 | D7: Can join normal games | E7: Leaderboard visibility only if admin allows | F7: 60
A8: 3 | B8: Trusted | C8: Credibility 70–79 | D8: Can join games and competitions | E8: No captain role yet | F8: 70
A9: 4 | B9: Competition Eligible | C9: Credibility 80–89 | D9: Can join competitions and become captain | E9: Monitored for disputes | F9: 80
A10: 5 | B10: Ambassador | C10: Credibility 90–100 | D10: Can captain, help organize, invite others | E10: Still subject to rules | F10: 90

Sheet Match Captains
A1: Match Captains
A2: Captains help verify attendance, scores, venue issues, and disputes.
A4: Captain_Assignment_ID | B4: Match_ID | C4: Captain_Player_ID | D4: Captain Name | E4: Game | F4: Area | G4: Credibility Score | H4: Responsibilities | I4: Status | J4: Assigned By | K4: Assigned At | L4: Notes
A5: CAP001 | B5: M001 | C5: P001 | D5: Ahmed Hassan | E5: Estimation | F5: New Cairo | G5: 77 | H5: Confirm attendance, submit score, report no-shows | I5: Assigned | J5: Marwan | K5: 46194 | L5: Sample
A6: CAP002 | B6: M002 | C6: P005 | D6: Youssef Tarek | E6: Padel | F6: Sheikh Zayed | G6: 70 | H6: Confirm venue, attendance, payment clarity, score | I6: Pending approval | J6: Marwan | K6: 46194 | L6: Sample

Sheet Make Blueprint
A1: Make Automation Blueprint V1
A2: Use normal Make scenarios for fixed logic and AI only for analysis, recommendations, message drafting, and reporting.
A4: Scenario # | B4: Scenario Name | C4: Trigger | D4: Reads From | E4: Checks / Conditions | F4: AI Used? | G4: Output | H4: Status Updated | I4: Manual Review? | J4: Owner
A5: 1 | B5: Player Registration | C5: New WhatsApp/Form submission | D5: Players, Rules Acceptance | E5: Required fields, consent, opt-in, approved venue acceptance | F5: No | G5: Create player record | H5: Player Status = Active/Incomplete | I5: If missing data | J5: Abdelrahman
A6: 2 | B6: Venue Registration | C6: New venue lead form | D6: Venues, Venue Agreements | E6: Venue type, area, games, pricing, terms accepted | F6: No | G6: Create venue lead | H6: Venue Status = Lead/Qualified | I6: Yes | J6: Marwan
A7: 3 | B7: Game Request Creation | C7: Player requests game | D7: Game Requests, Players | E7: Player active, cost accepted, location available | F7: No | G7: Create game request | H7: Request Status = Matching | I7: If player risk score low | J7: Abdelrahman
A8: 4 | B8: Match Suggestion | C8: New/open game request | D8: Players, Venues, Match Sessions | E8: Game, area, time, credibility, cost, venue availability | F8: Yes | G8: Suggested match session | H8: Match Status = Proposed | I8: Yes in MVP | J8: Both
A9: 5 | B9: Admin Approval | C9: Match proposed | D9: Match Sessions | E9: Enough players, approved venue, cost clear | F9: No | G9: Approval / rejection | H9: Admin Approved = Yes/No | I9: Yes | J9: Marwan
A10: 6 | B10: WhatsApp Invitation | C10: Admin approves match | D10: Confirmations, Message Log | E10: Opt-in, not opted out, timing at least 4h before | F10: AI drafts, template sends | G10: Send invitation | H10: Confirmation Status = Pending | I10: Spot-check | J10: Abdelrahman
A11: 7 | B11: Confirmation Tracking | C11: Player replies | D11: Confirmations | E11: Yes/No/Maybe/No response | F11: No | G11: Update confirmation | H11: Match status updates | I11: If required players not met | J11: Abdelrahman
A12: 8 | B12: Reminder | C12: Match confirmed | D12: Match Sessions, Confirmations | E12: Confirmed players only, correct timing | F12: No | G12: Send reminder | H12: Reminder Sent = Yes | I12: No | J12: Make
A13: 9 | B13: Score & Rating | C13: Game end time passed | D13: Scores, Ratings | E13: Match completed, captain verified | F13: Optional AI summary | G13: Send score/rating form | H13: Match Status = Completed/Review | I13: If disputed | J13: Abdelrahman
A14: 10 | B14: Incident Handling | C14: Report submitted | D14: Reports & Incidents | E14: Severity, history, evidence | F14: AI triage only | G14: Create admin task | H14: Incident Status = Under Review | I14: Always for serious issues | J14: Marwan
A15: 11 | B15: Venue Monthly Report | C15: Month end | D15: Venue Performance | E15: Games hosted, players sent, promos, ratings | F15: AI summary | G15: PDF/WhatsApp report | H15: Report Sent = Yes | I15: First month review | J15: Marwan

Sheet Operations Flow
A1: Operations Flow Graphs
A2: Arrow-based logic map showing where everything lives and how the workflow moves.
A4: PLAYER SIDE | B4: → | C4: Register | D4: → | E4: CRM Player Record | F4: → | G4: Game Request | H4: → | I4: Match Suggestion
C5: Rules + Consent | E5: Credibility Score | G5: Location + Time | I5: Admin Approval
A6: VENUE SIDE | B6: → | C6: Venue Lead | D6: → | E6: Contract + Subscription | F6: → | G6: Approved Venue | H6: → | I6: Match Venue
C7: Qualification | E7: Terms + Promotions | G7: Pricing + Availability | I7: Cost Split
A8: MATCH SIDE | B8: → | C8: WhatsApp Invite | D8: → | E8: Confirmations | F8: → | G8: Game Happens | H8: → | I8: Scores/Ratings
C9: Opt-in + Template | E9: Enough Players? | G9: Captain/Venue Check | I9: Leaderboards
A10: SAFETY SIDE | B10: → | C10: Incident Report | D10: → | E10: Admin Review | F10: → | G10: Penalty/Decision | H10: → | I10: Score Update
A13: Step | B13: Owner | C13: Tool/Table | D13: Action | E13: Decision / Output | F13: Next Step
A14: 1 | B14: Player | C14: WhatsApp/Form | D14: Submits profile, game, location, free time, consent | E14: Player record created | F14: CRM checks completeness
A15: 2 | B15: Make | C15: Players | D15: Checks required fields, opt-in, rules acceptance | E15: Active or missing data | F15: Ask missing questions
A16: 3 | B16: Player | C16: Game Request | D16: Requests game or joins available game | E16: Open game request | F16: Matching
A17: 4 | B17: Make + AI | C17: Players/Venues | D17: Suggests players and approved venue | E17: Proposed match | F17: Admin approval
A18: 5 | B18: Marwan | C18: Match Sessions | D18: Approves/rejects match | E18: Approved match | F18: WhatsApp invitation
A19: 6 | B19: Make | C19: WhatsApp/Confirmations | D19: Sends invitation and tracks replies | E19: Confirmed players count | F19: Reminder or replacement
A20: 7 | B20: Captain/Venue | C20: Match Captains | D20: Confirms attendance and game completed | E20: Completed/No-show/dispute | F20: Score/rating forms
A21: 8 | B21: Players | C21: Scores/Ratings | D21: Submit score, rating, incidents | E21: Scores, reports, feedback | F21: Update credibility/ranking
A22: 9 | B22: Abdelrahman | C22: Sheets/Make Logs | D22: Checks data quality and bot issues | E22: Fix logic gaps | F22: Improve system
A23: 10 | B23: Marwan | C23: Dashboard/Reports | D23: Reviews business performance | E23: Marketing/venue decisions | F23: Scale or adjust
